lepsen/core/__init__.py
lepsen/core/forceload.md
lepsen/core/load.md
lepsen/core/main.md
lepsen/core/player_head.md
lepsen/core/py.typed
lepsen/core/tick_scheduler.md
lepsen_core-0.1.2.dist-info/LICENSE
lepsen_core-0.1.2.dist-info/WHEEL
lepsen_core-0.1.2.dist-info/METADATA
lepsen_core-0.1.2.dist-info/RECORD
