Metadata-Version: 2.1
Name: lepsen-core
Version: 0.1.2
Summary: Minecraft data pack utility library.
Home-page: https://github.com/Luewd/lepsen-core
License: 0BSD
Author: Lue
Author-email: lue@lued.me
Requires-Python: >=3.9,<4.0
Classifier: License :: Freely Distributable
Classifier: License :: OSI Approved
Classifier: License :: Other/Proprietary License
Classifier: Programming Language :: Python :: 3
Classifier: Programming Language :: Python :: 3.9
Requires-Dist: beet (>=0.35.1,<0.37.0)
Requires-Dist: lectern (>=0.15.2,<0.16.0)
Project-URL: Repository, https://github.com/Luewd/lepsen-core
